{
    "id": "628274159398551562",
    "name": "Shayne Orok 💫",
    "description": "Shayne Orok's community Discord! (ﾉ◕ヮ◕)ﾉ*:･ﾟ✧",
    "icon": "080bb5c2782e4efbda5233026a66bee7",
    "splash": "8c240ab7922c6db20381816b11dd80db",
    "discovery_splash": "8c240ab7922c6db20381816b11dd80db",
    "banner": "904b4fc224728020d890b80241b69642",
    "approximate_presence_count": 1137,
    "approximate_member_count": 11274,
    "premium_subscription_count": 13,
    "preferred_locale": "en-US",
    "vanity_url_code": "shayneorok",
    "keywords": [
        "shayne orok",
        "anime",
        "manga"
    ],
    "features": [
        "ANIMATED_ICON",
        "BANNER",
        "COMMUNITY",
        "DISCOVERABLE",
        "ENABLED_DISCOVERABLE_BEFORE",
        "INVITE_SPLASH",
        "MEMBER_PROFILES",
        "MEMBER_VERIFICATION_GATE_ENABLED",
        "NEWS",
        "PARTNERED",
        "PREVIEW_ENABLED",
        "PRIVATE_THREADS",
        "ROLE_ICONS",
        "SEVEN_DAY_THREAD_ARCHIVE",
        "THREE_DAY_THREAD_ARCHIVE",
        "VANITY_URL",
        "VERIFIED",
        "VIP_REGIONS",
        "WELCOME_SCREEN_ENABLED"
    ],
    "partnered": true,
    "verified": true,
    "raw": {
        "id": "628274159398551562",
        "name": "Shayne Orok 💫",
        "description": "Shayne Orok's community Discord! (ﾉ◕ヮ◕)ﾉ*:･ﾟ✧",
        "icon": "080bb5c2782e4efbda5233026a66bee7",
        "splash": "8c240ab7922c6db20381816b11dd80db",
        "banner": "904b4fc224728020d890b80241b69642",
        "approximate_presence_count": 1137,
        "approximate_member_count": 11274,
        "premium_subscription_count": 13,
        "preferred_locale": "en-US",
        "auto_removed": false,
        "discovery_splash": "8c240ab7922c6db20381816b11dd80db",
        "primary_category_id": 2,
        "vanity_url_code": "shayneorok",
        "is_published": false,
        "keywords": [
            "shayne orok",
            "anime",
            "manga"
        ],
        "features": [
            "ANIMATED_ICON",
            "BANNER",
            "COMMUNITY",
            "DISCOVERABLE",
            "ENABLED_DISCOVERABLE_BEFORE",
            "INVITE_SPLASH",
            "MEMBER_PROFILES",
            "MEMBER_VERIFICATION_GATE_ENABLED",
            "NEWS",
            "PARTNERED",
            "PREVIEW_ENABLED",
            "PRIVATE_THREADS",
            "ROLE_ICONS",
            "SEVEN_DAY_THREAD_ARCHIVE",
            "THREE_DAY_THREAD_ARCHIVE",
            "VANITY_URL",
            "VERIFIED",
            "VIP_REGIONS",
            "WELCOME_SCREEN_ENABLED"
        ]
    }
}