{
    "id": "428629452222627881",
    "name": "Ant Workshop",
    "description": "Come and chat with the developers about our games!",
    "icon": "91593e0d7854e18fc17608e4b7228e3a",
    "splash": null,
    "discovery_splash": null,
    "banner": null,
    "approximate_presence_count": 35,
    "approximate_member_count": 273,
    "premium_subscription_count": 0,
    "preferred_locale": "en-US",
    "vanity_url_code": "antworkshop",
    "keywords": null,
    "features": [
        "AUTO_MODERATION",
        "COMMUNITY",
        "DISCOVERABLE",
        "FEATURABLE",
        "INVITE_SPLASH",
        "NEWS",
        "PREVIEW_ENABLED",
        "VANITY_URL",
        "VERIFIED",
        "WELCOME_SCREEN_ENABLED"
    ],
    "partnered": false,
    "verified": true,
    "raw": {
        "approximate_member_count": 273,
        "approximate_presence_count": 35,
        "auto_removed": false,
        "banner": null,
        "description": "Come and chat with the developers about our games!",
        "discovery_splash": null,
        "features": [
            "AUTO_MODERATION",
            "COMMUNITY",
            "DISCOVERABLE",
            "FEATURABLE",
            "INVITE_SPLASH",
            "NEWS",
            "PREVIEW_ENABLED",
            "VANITY_URL",
            "VERIFIED",
            "WELCOME_SCREEN_ENABLED"
        ],
        "icon": "91593e0d7854e18fc17608e4b7228e3a",
        "id": "428629452222627881",
        "is_published": false,
        "keywords": null,
        "name": "Ant Workshop",
        "preferred_locale": "en-US",
        "premium_subscription_count": 0,
        "primary_category_id": 0,
        "splash": null,
        "vanity_url_code": "antworkshop"
    }
}