{
    "id": "284247906322612224",
    "name": "Tall Guy Productions",
    "description": "Play, Discuss and Connect with fans of - and the development team behind - Apotheorasis, Lil' Arena, and other games.",
    "icon": "0bf5f34cd54f0694027eb9a47c3be529",
    "splash": "22cfa90988c9ee2aea514de4b6913742",
    "discovery_splash": "530ddd83abd97f3aa356446f0ade766d",
    "banner": null,
    "approximate_presence_count": 42,
    "approximate_member_count": 262,
    "premium_subscription_count": 0,
    "preferred_locale": "en-US",
    "vanity_url_code": "tallguyprods",
    "keywords": [],
    "features": [
        "CHANNEL_ICON_EMOJIS_GENERATED",
        "COMMUNITY",
        "DISCOVERABLE",
        "ENABLED_DISCOVERABLE_BEFORE",
        "FEATURABLE",
        "INVITE_SPLASH",
        "NEWS",
        "PREVIEW_ENABLED",
        "VANITY_URL",
        "VERIFIED",
        "WELCOME_SCREEN_ENABLED"
    ],
    "partnered": false,
    "verified": true,
    "raw": {
        "id": "284247906322612224",
        "name": "Tall Guy Productions",
        "description": "Play, Discuss and Connect with fans of - and the development team behind - Apotheorasis, Lil' Arena, and other games.",
        "icon": "0bf5f34cd54f0694027eb9a47c3be529",
        "splash": "22cfa90988c9ee2aea514de4b6913742",
        "banner": null,
        "approximate_presence_count": 42,
        "approximate_member_count": 262,
        "premium_subscription_count": 0,
        "preferred_locale": "en-US",
        "auto_removed": false,
        "discovery_splash": "530ddd83abd97f3aa356446f0ade766d",
        "primary_category_id": 1,
        "vanity_url_code": "tallguyprods",
        "is_published": false,
        "keywords": [],
        "features": [
            "CHANNEL_ICON_EMOJIS_GENERATED",
            "COMMUNITY",
            "DISCOVERABLE",
            "ENABLED_DISCOVERABLE_BEFORE",
            "FEATURABLE",
            "INVITE_SPLASH",
            "NEWS",
            "PREVIEW_ENABLED",
            "VANITY_URL",
            "VERIFIED",
            "WELCOME_SCREEN_ENABLED"
        ]
    }
}