{
    "id": "498874578349850644",
    "name": "Fortnite Fam",
    "description": "A server with active LFG, Tournaments, game discussion, events, advertising and more! Join us today!",
    "icon": "a_15af2ee752c12573fc5062d57f2a0dae",
    "splash": "ce1c03fa02227849dda94c6018da3088",
    "discovery_splash": "05679f625ac9e13edf9ba47b36c18c81",
    "banner": "12dda8dfe39e0221aa3b69741f56ad61",
    "approximate_presence_count": 7181,
    "approximate_member_count": 111100,
    "premium_subscription_count": 7,
    "preferred_locale": "en-US",
    "vanity_url_code": "tkfortnite",
    "keywords": [
        "Fortnite",
        "Fortnite Battle Royale",
        "Tournaments",
        "LFG",
        "Zonewars",
        "Boxfights",
        "Save the World",
        "Fortnite Discord",
        "Fortnite Discord Server",
        "FN"
    ],
    "features": [
        "ANIMATED_ICON",
        "AUTOMOD_TRIGGER_ML_SPAM_FILTER",
        "AUTOMOD_TRIGGER_SPAM_LINK_FILTER",
        "AUTOMOD_TRIGGER_USER_PROFILE",
        "AUTO_MODERATION",
        "BANNER",
        "CHANNEL_ICON_EMOJIS_GENERATED",
        "COMMUNITY",
        "DISCOVERABLE",
        "ENABLED_DISCOVERABLE_BEFORE",
        "GUILD_HOME_TEST",
        "GUILD_WEB_PAGE_VANITY_URL",
        "INVITE_SPLASH",
        "MEMBER_PROFILES",
        "NEWS",
        "NEW_THREAD_PERMISSIONS",
        "PREVIEW_ENABLED",
        "PRIVATE_THREADS",
        "ROLE_ICONS",
        "SEVEN_DAY_THREAD_ARCHIVE",
        "SOUNDBOARD",
        "THREADS_ENABLED",
        "THREE_DAY_THREAD_ARCHIVE",
        "VANITY_URL",
        "VERIFIED",
        "WELCOME_SCREEN_ENABLED"
    ],
    "partnered": false,
    "verified": true,
    "raw": {
        "id": "498874578349850644",
        "name": "Fortnite Fam",
        "description": "A server with active LFG, Tournaments, game discussion, events, advertising and more! Join us today!",
        "icon": "a_15af2ee752c12573fc5062d57f2a0dae",
        "splash": "ce1c03fa02227849dda94c6018da3088",
        "banner": "12dda8dfe39e0221aa3b69741f56ad61",
        "approximate_presence_count": 7181,
        "approximate_member_count": 111100,
        "premium_subscription_count": 7,
        "preferred_locale": "en-US",
        "auto_removed": false,
        "discovery_splash": "05679f625ac9e13edf9ba47b36c18c81",
        "primary_category_id": 1,
        "vanity_url_code": "tkfortnite",
        "is_published": true,
        "keywords": [
            "Fortnite",
            "Fortnite Battle Royale",
            "Tournaments",
            "LFG",
            "Zonewars",
            "Boxfights",
            "Save the World",
            "Fortnite Discord",
            "Fortnite Discord Server",
            "FN"
        ],
        "features": [
            "ANIMATED_ICON",
            "AUTOMOD_TRIGGER_ML_SPAM_FILTER",
            "AUTOMOD_TRIGGER_SPAM_LINK_FILTER",
            "AUTOMOD_TRIGGER_USER_PROFILE",
            "AUTO_MODERATION",
            "BANNER",
            "CHANNEL_ICON_EMOJIS_GENERATED",
            "COMMUNITY",
            "DISCOVERABLE",
            "ENABLED_DISCOVERABLE_BEFORE",
            "GUILD_HOME_TEST",
            "GUILD_WEB_PAGE_VANITY_URL",
            "INVITE_SPLASH",
            "MEMBER_PROFILES",
            "NEWS",
            "NEW_THREAD_PERMISSIONS",
            "PREVIEW_ENABLED",
            "PRIVATE_THREADS",
            "ROLE_ICONS",
            "SEVEN_DAY_THREAD_ARCHIVE",
            "SOUNDBOARD",
            "THREADS_ENABLED",
            "THREE_DAY_THREAD_ARCHIVE",
            "VANITY_URL",
            "VERIFIED",
            "WELCOME_SCREEN_ENABLED"
        ]
    }
}