{
    "id": "862236243458129941",
    "name": "TENISTAS",
    "description": "",
    "icon": "a_838ab175f3a953228444fe5b07a15cde",
    "splash": "f385e72b118a45f7d44ada02d6e16820",
    "discovery_splash": "f385e72b118a45f7d44ada02d6e16820",
    "banner": "12d9504bb0ac1e34bdafeb46b423deab",
    "approximate_presence_count": 2054,
    "approximate_member_count": 12733,
    "premium_subscription_count": 36,
    "preferred_locale": "es-ES",
    "vanity_url_code": "tenie",
    "keywords": [
        "comunidad",
        "genshin",
        "juegos",
        "streamer",
        "twitch",
        "youtube"
    ],
    "features": [
        "ANIMATED_BANNER",
        "ANIMATED_ICON",
        "AUTO_MODERATION",
        "BANNER",
        "CHANNEL_ICON_EMOJIS_GENERATED",
        "COMMUNITY",
        "COMMUNITY_EXP_LARGE_UNGATED",
        "DISCOVERABLE",
        "ENABLED_DISCOVERABLE_BEFORE",
        "GUILD_WEB_PAGE_VANITY_URL",
        "INVITE_SPLASH",
        "MEMBER_PROFILES",
        "MEMBER_VERIFICATION_GATE_ENABLED",
        "NEWS",
        "NEW_THREAD_PERMISSIONS",
        "PARTNERED",
        "PREVIEW_ENABLED",
        "PRIVATE_THREADS",
        "ROLE_ICONS",
        "SEVEN_DAY_THREAD_ARCHIVE",
        "SOUNDBOARD",
        "TEXT_IN_VOICE_ENABLED",
        "THREADS_ENABLED",
        "THREE_DAY_THREAD_ARCHIVE",
        "VANITY_URL",
        "VIP_REGIONS",
        "WELCOME_SCREEN_ENABLED"
    ],
    "partnered": true,
    "verified": false,
    "raw": {
        "id": "862236243458129941",
        "name": "TENISTAS",
        "description": "",
        "icon": "a_838ab175f3a953228444fe5b07a15cde",
        "splash": "f385e72b118a45f7d44ada02d6e16820",
        "banner": "12d9504bb0ac1e34bdafeb46b423deab",
        "approximate_presence_count": 2054,
        "approximate_member_count": 12733,
        "premium_subscription_count": 36,
        "preferred_locale": "es-ES",
        "auto_removed": false,
        "discovery_splash": "f385e72b118a45f7d44ada02d6e16820",
        "primary_category_id": 14,
        "vanity_url_code": "tenie",
        "is_published": false,
        "keywords": [
            "comunidad",
            "genshin",
            "juegos",
            "streamer",
            "twitch",
            "youtube"
        ],
        "features": [
            "ANIMATED_BANNER",
            "ANIMATED_ICON",
            "AUTO_MODERATION",
            "BANNER",
            "CHANNEL_ICON_EMOJIS_GENERATED",
            "COMMUNITY",
            "COMMUNITY_EXP_LARGE_UNGATED",
            "DISCOVERABLE",
            "ENABLED_DISCOVERABLE_BEFORE",
            "GUILD_WEB_PAGE_VANITY_URL",
            "INVITE_SPLASH",
            "MEMBER_PROFILES",
            "MEMBER_VERIFICATION_GATE_ENABLED",
            "NEWS",
            "NEW_THREAD_PERMISSIONS",
            "PARTNERED",
            "PREVIEW_ENABLED",
            "PRIVATE_THREADS",
            "ROLE_ICONS",
            "SEVEN_DAY_THREAD_ARCHIVE",
            "SOUNDBOARD",
            "TEXT_IN_VOICE_ENABLED",
            "THREADS_ENABLED",
            "THREE_DAY_THREAD_ARCHIVE",
            "VANITY_URL",
            "VIP_REGIONS",
            "WELCOME_SCREEN_ENABLED"
        ]
    }
}