{
    "id": "730445854938497114",
    "name": "calebmusik21",
    "description": "The Official server of Caleb Santos - Singer-Songwriter | Actor | Music Producer #CalebSantosGAMING",
    "icon": "f6515c7a4927d03af61783a938a3d439",
    "splash": "ca217af4b7236186e65768e2638b3505",
    "discovery_splash": "dad4b994039a36fe6fcf81913edd16b3",
    "banner": null,
    "approximate_presence_count": 4,
    "approximate_member_count": 78,
    "premium_subscription_count": 0,
    "preferred_locale": "en-US",
    "vanity_url_code": "calebmusik21",
    "keywords": [
        "Caleb Santos",
        "calebmusik21",
        "Caleb Santos GAMING",
        "Game Night",
        "Facebook Gaming",
        "Caleb Santos Official Channel",
        "calebmusik21 server"
    ],
    "features": [
        "AUTO_MODERATION",
        "COMMUNITY",
        "DISCOVERABLE",
        "ENABLED_DISCOVERABLE_BEFORE",
        "EXPOSED_TO_ACTIVITIES_WTP_EXPERIMENT",
        "INVITE_SPLASH",
        "NEWS",
        "PREVIEW_ENABLED",
        "THREADS_ENABLED",
        "VANITY_URL",
        "VERIFIED",
        "WELCOME_SCREEN_ENABLED"
    ],
    "partnered": false,
    "verified": true,
    "raw": {
        "id": "730445854938497114",
        "name": "calebmusik21",
        "description": "The Official server of Caleb Santos - Singer-Songwriter | Actor | Music Producer #CalebSantosGAMING",
        "icon": "f6515c7a4927d03af61783a938a3d439",
        "splash": "ca217af4b7236186e65768e2638b3505",
        "banner": null,
        "approximate_presence_count": 4,
        "approximate_member_count": 78,
        "premium_subscription_count": 0,
        "preferred_locale": "en-US",
        "auto_removed": false,
        "discovery_splash": "dad4b994039a36fe6fcf81913edd16b3",
        "primary_category_id": 1,
        "vanity_url_code": "calebmusik21",
        "is_published": true,
        "keywords": [
            "Caleb Santos",
            "calebmusik21",
            "Caleb Santos GAMING",
            "Game Night",
            "Facebook Gaming",
            "Caleb Santos Official Channel",
            "calebmusik21 server"
        ],
        "features": [
            "AUTO_MODERATION",
            "COMMUNITY",
            "DISCOVERABLE",
            "ENABLED_DISCOVERABLE_BEFORE",
            "EXPOSED_TO_ACTIVITIES_WTP_EXPERIMENT",
            "INVITE_SPLASH",
            "NEWS",
            "PREVIEW_ENABLED",
            "THREADS_ENABLED",
            "VANITY_URL",
            "VERIFIED",
            "WELCOME_SCREEN_ENABLED"
        ]
    }
}